fsm_hub/__init__.py
fsm_hub/__main__.py
fsm_hub/app.py
fsm_hub/cli.py
fsm_hub/core.py
fsm_hub/entities.py
fsm_hub-3.2.data/scripts/fsm-hub
fsm_hub-3.2.data/scripts/fsm-step
fsm_hub-3.2.dist-info/METADATA
fsm_hub-3.2.dist-info/WHEEL
fsm_hub-3.2.dist-info/top_level.txt
fsm_hub-3.2.dist-info/RECORD
